bibtexparser/__init__.py
bibtexparser/bibdatabase.py
bibtexparser/bibtexexpression.py
bibtexparser/bparser.py
bibtexparser/bwriter.py
bibtexparser/customization.py
bibtexparser/latexenc.py
bibtexparser-1.3.0.dist-info/COPYING
bibtexparser-1.3.0.dist-info/METADATA
bibtexparser-1.3.0.dist-info/WHEEL
bibtexparser-1.3.0.dist-info/top_level.txt
bibtexparser-1.3.0.dist-info/RECORD
