Metadata-Version: 2.1
Name: bibtexparser
Version: 1.3.0
Summary: Bibtex parser for python 3
Home-page: https://github.com/sciunto-org/python-bibtexparser
Author: Francois Boulogne and other contributors
Author-email: devel@sciunto.org
License: LGPLv3 or BSD
Platform: UNKNOWN
License-File: COPYING
